wiznote/__init__.py
wiznote/core.py
wiznote/error.py
wiznote-2.0.0.dist-info/METADATA
wiznote-2.0.0.dist-info/WHEEL
wiznote-2.0.0.dist-info/top_level.txt
wiznote-2.0.0.dist-info/RECORD
