Metadata-Version: 2.1
Name: wiznote
Version: 2.0.0
Summary: Wiz Open API In Python.
Home-page: https://github.com/536/wiznote
Author: https://github.com/536
License: MIT
Project-URL: Documentation, https://www.wiz.cn/wapp/pages/book/bb8f0f10-48ca-11ea-b27a-ef51fb9d4bb4
Project-URL: Source, https://github.com/536/wiznote
Platform: UNKNOWN
Classifier: Programming Language :: Python :: 3.6
Classifier: Programming Language :: Python :: 3.7
Classifier: Programming Language :: Python :: 3.8
Classifier: Programming Language :: Python :: 3.9
Classifier: License :: OSI Approved :: MIT License
Requires-Python: >=3.6
Requires-Dist: requests
